odoo/addons/shopinvader_api_payment_provider_custom/README.rst
odoo/addons/shopinvader_api_payment_provider_custom/__init__.py
odoo/addons/shopinvader_api_payment_provider_custom/__manifest__.py
odoo/addons/shopinvader_api_payment_provider_custom/i18n/shopinvader_api_payment_provider_custom.pot
odoo/addons/shopinvader_api_payment_provider_custom/readme/CONTRIBUTORS.rst
odoo/addons/shopinvader_api_payment_provider_custom/readme/DESCRIPTION.rst
odoo/addons/shopinvader_api_payment_provider_custom/readme/USAGE.rst
odoo/addons/shopinvader_api_payment_provider_custom/routers/__init__.py
odoo/addons/shopinvader_api_payment_provider_custom/routers/payment_custom.py
odoo/addons/shopinvader_api_payment_provider_custom/static/description/index.html
odoo_addon_shopinvader_api_payment_provider_custom-16.0.1.0.0.4.dist-info/METADATA
odoo_addon_shopinvader_api_payment_provider_custom-16.0.1.0.0.4.dist-info/WHEEL
odoo_addon_shopinvader_api_payment_provider_custom-16.0.1.0.0.4.dist-info/top_level.txt
odoo_addon_shopinvader_api_payment_provider_custom-16.0.1.0.0.4.dist-info/RECORD
